configuration_phi3_v.cpython-310-x86_64-linux-gnu.so
modeling_phi3_v.cpython-310-x86_64-linux-gnu.so
processing_phi3_v.cpython-310-x86_64-linux-gnu.so
vllm_patch.cpython-310-x86_64-linux-gnu.so
factory_sdk/__init__.py
factory_sdk/__main__.py
factory_sdk/client.py
factory_sdk/logging.py
factory_sdk/adapters/__init__.py
factory_sdk/datasets/__init__.py
factory_sdk/datasets/arrow.py
factory_sdk/datasets/hf.py
factory_sdk/deployment/__init__.py
factory_sdk/deployment/api_server.py
factory_sdk/deployment/merge.py
factory_sdk/deployment/quantization.py
factory_sdk/deployment/run.py
factory_sdk/deployment/start.py
factory_sdk/deployment/start_merge.py
factory_sdk/dto/__init__.py
factory_sdk/dto/adapter.py
factory_sdk/dto/dataset.py
factory_sdk/dto/deployment.py
factory_sdk/dto/evaluation.py
factory_sdk/dto/metric.py
factory_sdk/dto/model.py
factory_sdk/dto/payments.py
factory_sdk/dto/preprocessor.py
factory_sdk/dto/project.py
factory_sdk/dto/recipe.py
factory_sdk/dto/resource.py
factory_sdk/dto/task.py
factory_sdk/dto/tenant.py
factory_sdk/dto/user.py
factory_sdk/environment/__init__.py
factory_sdk/eval/__init__.py
factory_sdk/eval/run.py
factory_sdk/eval/start.py
factory_sdk/evaluation/__init__.py
factory_sdk/exceptions/__init__.py
factory_sdk/exceptions/api.py
factory_sdk/fast/__init__.py
factory_sdk/fast/args.c
factory_sdk/fast/args.cpython-310-x86_64-linux-gnu.so
factory_sdk/fast/inspect.c
factory_sdk/fast/inspect.cpython-310-x86_64-linux-gnu.so
factory_sdk/fast/progress.c
factory_sdk/fast/progress.cpython-310-x86_64-linux-gnu.so
factory_sdk/fast/progressBackup.c
factory_sdk/fast/progressBackup.cpython-310-x86_64-linux-gnu.so
factory_sdk/fast/algorithms/__init__.py
factory_sdk/fast/algorithms/iforest.c
factory_sdk/fast/algorithms/iforest.cpython-310-x86_64-linux-gnu.so
factory_sdk/fast/algorithms/mmd.c
factory_sdk/fast/algorithms/mmd.cpython-310-x86_64-linux-gnu.so
factory_sdk/fast/deployment/__init__.py
factory_sdk-0.0.93.dist-info/METADATA
factory_sdk-0.0.93.dist-info/WHEEL
factory_sdk-0.0.93.dist-info/top_level.txt
factory_sdk-0.0.93.dist-info/RECORD
