Metadata-Version: 2.4
Name: factory-sdk
Version: 0.0.93
Summary: factory SDK
Author: manufactAI <dev@manufactai.com>
Requires-Python: >=3.10
Requires-Dist: transformers==4.51.3
Requires-Dist: datasets<4.0.0,>=3.2.0
Requires-Dist: joblib<2.0.0,>=1.4.2
Requires-Dist: pillow<12.0.0,>=11.1.0
Requires-Dist: pydantic<3.0.0,>=2.10.6
Requires-Dist: rich<14.0.0,>=13.9.4
Requires-Dist: black<26.0.0,>=25.1.0
Requires-Dist: scikit-learn<2.0.0,>=1.6.1
Requires-Dist: sentence-transformers<5.0.0,>=4.0.1
Requires-Dist: requests-toolbelt<2.0.0,>=1.0.0
Requires-Dist: peft==0.15.1
Requires-Dist: deepspeed==0.16.5
Requires-Dist: gputil<2.0.0,>=1.4.0
Requires-Dist: tqdm<5.0.0,>=4.67.1
Requires-Dist: vllm==0.8.2
Requires-Dist: pycryptodome<4.0.0,>=3.21.0
Requires-Dist: zeus==0.11.0
Requires-Dist: nvidia-ml-py<13.0.0,>=12.570.86
Requires-Dist: optimum<2.0.0,>=1.24.0
Requires-Dist: onnxruntime<2.0.0,>=1.20.1
Requires-Dist: onnx<2.0.0,>=1.17.0
Requires-Dist: huggingface-hub==0.30.2
Requires-Dist: accelerate==1.5.2
Requires-Dist: trl==0.17.0
Requires-Dist: bitsandbytes==0.45.5
Dynamic: author
Dynamic: requires-dist
Dynamic: requires-python
Dynamic: summary
